{"success":true,"kpi":{"totalGmv":527000.5,"totalNetGmv":527000.5,"totalOrders":192,"avgOrderValue":2745,"avgRoi":2.1,"projectCount":5,"activeProjects":5,"totalTargetGmv":632400.6,"targetCompletionRate":83.3},"channelBreakdown":{"liveGmv":0,"shortVideoGmv":0,"productCardGmv":0,"showcaseGmv":0},"hasChannelBreakdown":false,"funnelAggregated":{"live":{"totalSessions":27,"totalViewers":7100,"totalClicks":1065,"totalOrders":175,"totalGmv":87500},"shortVideo":{"totalPublish":53,"totalExposure":18300,"avgRetention3s":0.6859999999999999,"avgCompletion":0.316,"totalClicks":1584,"totalOrders":109,"totalGmv":54500}},"projects":[{"recordId":"recxEe1iwiaLce","projectId":"睿逸行","projectType":"全案代运营","projectStatus":"进行中","deadline":1785427200000,"remainingDays":"还有10天到期","targetGmv":150000,"orderGmv":0,"paidGmv":0,"refundGmv":0,"netGmv":125000,"totalExposure":0,"clickCount":0,"orderCount":45,"avgOrderValue":2777.777777777778,"liveGmvRatio":0,"shortVideoGmv":0,"shortVideoGmvRatio":0,"productCardGmv":0,"productCardGmvRatio":0,"showcaseGmv":0,"showcaseGmvRatio":0,"totalLiveGmv":0,"totalLiveSessions":0,"avgLiveViewers":0,"liveCompletionRate":0,"roi":2.3,"liveGmv":0},{"recordId":"recd7QiDGFwtfH","projectId":"MIND CRUISER LIMITED （Speak On）","projectType":"全案代运营","projectStatus":"进行中","deadline":1814284800000,"remainingDays":"还有344天到期","targetGmv":106800.59999999999,"orderGmv":0,"paidGmv":0,"refundGmv":0,"netGmv":89000.5,"totalExposure":0,"clickCount":0,"orderCount":32,"avgOrderValue":2781.265625,"liveGmvRatio":0,"shortVideoGmv":0,"shortVideoGmvRatio":0,"productCardGmv":0,"productCardGmvRatio":0,"showcaseGmv":0,"showcaseGmvRatio":0,"totalLiveGmv":0,"totalLiveSessions":0,"avgLiveViewers":0,"liveCompletionRate":0,"roi":1.8,"liveGmv":0},{"recordId":"recDXkR3ZzokM9","projectId":"保健品客户Ingreen","projectType":"全案代运营","projectStatus":"进行中","deadline":1789401600000,"remainingDays":"还有56天到期","targetGmv":78000,"orderGmv":0,"paidGmv":0,"refundGmv":0,"netGmv":65000,"totalExposure":0,"clickCount":0,"orderCount":20,"avgOrderValue":3250,"liveGmvRatio":0,"shortVideoGmv":0,"shortVideoGmvRatio":0,"productCardGmv":0,"productCardGmvRatio":0,"showcaseGmv":0,"showcaseGmvRatio":0,"totalLiveGmv":0,"totalLiveSessions":0,"avgLiveViewers":0,"liveCompletionRate":0,"roi":1.5,"liveGmv":0},{"recordId":"rec0MC5LPpJVzw","projectId":"JML","projectType":"全案代运营","projectStatus":"进行中","deadline":1784217600000,"remainingDays":"已过期4天","targetGmv":180000,"orderGmv":0,"paidGmv":0,"refundGmv":0,"netGmv":150000,"totalExposure":0,"clickCount":0,"orderCount":60,"avgOrderValue":2500,"liveGmvRatio":0,"shortVideoGmv":0,"shortVideoGmvRatio":0,"productCardGmv":0,"productCardGmvRatio":0,"showcaseGmv":0,"showcaseGmvRatio":0,"totalLiveGmv":0,"totalLiveSessions":0,"avgLiveViewers":0,"liveCompletionRate":0,"roi":3,"liveGmv":0},{"recordId":"reczIHIQI7pW7F","projectId":"弗瑞登筋膜刀客户","projectType":"全案代运营","projectStatus":"进行中","deadline":null,"remainingDays":"","targetGmv":117600,"orderGmv":0,"paidGmv":0,"refundGmv":0,"netGmv":98000,"totalExposure":0,"clickCount":0,"orderCount":35,"avgOrderValue":2800,"liveGmvRatio":0,"shortVideoGmv":0,"shortVideoGmvRatio":0,"productCardGmv":0,"productCardGmvRatio":0,"showcaseGmv":0,"showcaseGmvRatio":0,"totalLiveGmv":0,"totalLiveSessions":0,"avgLiveViewers":0,"liveCompletionRate":0,"roi":1.9,"liveGmv":0}],"channels":[{"projectId":"睿逸行","linkRecordId":"recxEe1iwiaLce","liveGmv":0,"liveGmvRatio":0,"shortVideoGmv":0,"shortVideoGmvRatio":0,"productCardGmv":0,"productCardGmvRatio":0,"showcaseGmv":0,"showcaseGmvRatio":0,"gmv":125000,"orderCount":45,"roi":2.3,"ratioAuto":0},{"projectId":"MIND CRUISER LIMITED （Speak On）","linkRecordId":"recd7QiDGFwtfH","liveGmv":0,"liveGmvRatio":0,"shortVideoGmv":0,"shortVideoGmvRatio":0,"productCardGmv":0,"productCardGmvRatio":0,"showcaseGmv":0,"showcaseGmvRatio":0,"gmv":89000.5,"orderCount":32,"roi":1.8,"ratioAuto":0},{"projectId":"保健品客户Ingreen","linkRecordId":"recDXkR3ZzokM9","liveGmv":0,"liveGmvRatio":0,"shortVideoGmv":0,"shortVideoGmvRatio":0,"productCardGmv":0,"productCardGmvRatio":0,"showcaseGmv":0,"showcaseGmvRatio":0,"gmv":65000,"orderCount":20,"roi":1.5,"ratioAuto":0},{"projectId":"JML","linkRecordId":"rec0MC5LPpJVzw","liveGmv":0,"liveGmvRatio":0,"shortVideoGmv":0,"shortVideoGmvRatio":0,"productCardGmv":0,"productCardGmvRatio":0,"showcaseGmv":0,"showcaseGmvRatio":0,"gmv":150000,"orderCount":60,"roi":3,"ratioAuto":0},{"projectId":"弗瑞登筋膜刀客户","linkRecordId":"reczIHIQI7pW7F","liveGmv":0,"liveGmvRatio":0,"shortVideoGmv":0,"shortVideoGmvRatio":0,"productCardGmv":0,"productCardGmvRatio":0,"showcaseGmv":0,"showcaseGmvRatio":0,"gmv":98000,"orderCount":35,"roi":1.9,"ratioAuto":0}],"funnels":[{"bloggerId":[{"text":"1","type":"text"}],"funnelType":"直播","liveSessions":5,"viewers":1200,"productClicks":180,"liveOrders":30,"liveGmv":15000,"publishCount":8,"exposure":2500,"retention3s":0.65,"completionRate":0.35,"ctr":0.15,"shortVideoOrders":15,"shortVideoGmv":7500},{"bloggerId":[{"text":"2","type":"text"}],"funnelType":"短视频","liveSessions":8,"viewers":2500,"productClicks":420,"liveOrders":70,"liveGmv":35000,"publishCount":12,"exposure":4800,"retention3s":0.72,"completionRate":0.28,"ctr":0.17,"shortVideoOrders":25,"shortVideoGmv":12500},{"bloggerId":[{"text":"3","type":"text"}],"funnelType":"直播","liveSessions":3,"viewers":800,"productClicks":120,"liveOrders":20,"liveGmv":10000,"publishCount":5,"exposure":1500,"retention3s":0.6,"completionRate":0.3,"ctr":0.1,"shortVideoOrders":8,"shortVideoGmv":4000},{"bloggerId":[{"text":"4","type":"text"}],"funnelType":"短视频","liveSessions":6,"viewers":1800,"productClicks":300,"liveOrders":50,"liveGmv":25000,"publishCount":10,"exposure":3200,"retention3s":0.68,"completionRate":0.32,"ctr":0.17,"shortVideoOrders":20,"shortVideoGmv":10000},{"bloggerId":[{"text":"5","type":"text"}],"funnelType":"直播","liveSessions":10,"viewers":3000,"productClicks":450,"liveOrders":75,"liveGmv":37500,"publishCount":15,"exposure":5000,"retention3s":0.7,"completionRate":0.25,"ctr":0.15,"shortVideoOrders":35,"shortVideoGmv":17500},{"bloggerId":[{"text":"6","type":"text"}],"funnelType":"短视频","liveSessions":4,"viewers":1000,"productClicks":180,"liveOrders":30,"liveGmv":15000,"publishCount":6,"exposure":2000,"retention3s":0.62,"completionRate":0.38,"ctr":0.18,"shortVideoOrders":12,"shortVideoGmv":6000},{"bloggerId":[{"text":"7","type":"text"}],"funnelType":"直播","liveSessions":7,"viewers":1500,"productClicks":225,"liveOrders":35,"liveGmv":17500,"publishCount":9,"exposure":3000,"retention3s":0.66,"completionRate":0.34,"ctr":0.12,"shortVideoOrders":22,"shortVideoGmv":11000},{"bloggerId":[{"text":"8","type":"text"}],"funnelType":"短视频","liveSessions":9,"viewers":2200,"productClicks":396,"liveOrders":66,"liveGmv":33000,"publishCount":14,"exposure":4500,"retention3s":0.71,"completionRate":0.3,"ctr":0.18,"shortVideoOrders":30,"shortVideoGmv":15000},{"bloggerId":[{"text":"9","type":"text"}],"funnelType":"直播","liveSessions":2,"viewers":600,"productClicks":90,"liveOrders":15,"liveGmv":7500,"publishCount":4,"exposure":1200,"retention3s":0.58,"completionRate":0.32,"ctr":0.08,"shortVideoOrders":5,"shortVideoGmv":2500},{"bloggerId":[{"text":"10","type":"text"}],"funnelType":"短视频","liveSessions":5,"viewers":1600,"productClicks":288,"liveOrders":48,"liveGmv":24000,"publishCount":11,"exposure":3800,"retention3s":0.7,"completionRate":0.3,"ctr":0.18,"shortVideoOrders":22,"shortVideoGmv":11000},{"bloggerId":"","funnelType":"","liveSessions":0,"viewers":0,"productClicks":0,"liveOrders":0,"liveGmv":0,"publishCount":0,"exposure":0,"retention3s":0,"completionRate":0,"ctr":0,"shortVideoOrders":0,"shortVideoGmv":0},{"bloggerId":"","funnelType":"","liveSessions":0,"viewers":0,"productClicks":0,"liveOrders":0,"liveGmv":0,"publishCount":0,"exposure":0,"retention3s":0,"completionRate":0,"ctr":0,"shortVideoOrders":0,"shortVideoGmv":0}],"liveSessions":[{"sessionId":"1","date":null,"topic":"","host":"","totalViewers":0,"peakViewers":0,"avgWatchTime":0,"liveGmv":0,"orderCount":0,"refundAmount":0,"netGmv":0,"adSpend":0,"roi":0,"productClicks":0,"newFollowers":0,"status":"","projectLink":"JML,保健品客户Ingreen,MIND CRUISER LIMITED （Speak On）,睿逸行,弗瑞登筋膜刀客户","projectTargetGmv":0},{"sessionId":"2","date":null,"topic":"","host":"","totalViewers":0,"peakViewers":0,"avgWatchTime":0,"liveGmv":0,"orderCount":0,"refundAmount":0,"netGmv":0,"adSpend":0,"roi":0,"productClicks":0,"newFollowers":0,"status":"","projectLink":"JML,保健品客户Ingreen,MIND CRUISER LIMITED （Speak On）,睿逸行,弗瑞登筋膜刀客户","projectTargetGmv":0}],"lastUpdated":"2026-07-21T00:16:03.216Z"}